simmer/__init__.py
simmer/add_dark_exp.py
simmer/analyze_image.py
simmer/badpix.fits
simmer/check_logsheet.py
simmer/contrast.py
simmer/create_config.py
simmer/darks.py
simmer/drivers.py
simmer/flats.py
simmer/image.py
simmer/insts.py
simmer/make_triceratops_contrasts.py
simmer/plotting.py
simmer/registration.py
simmer/run_night.py
simmer/scipy_utils.py
simmer/search_headers.py
simmer/sky.py
simmer/summarize.py
simmer/utils.py
simmer/validate_config.py
simmer/Examples/__init__.py
simmer/Examples/PHARO/__init__.py
simmer/Examples/PHARO/logsheet.csv
simmer/Examples/Shane/__init__.py
simmer/Examples/Shane/logsheet.xlsx
simmer/Examples/Shane/logsheet_incorrect.xlsx
simmer/Examples/Shane/~$logsheet_incorrect.xlsx
simmer/schemas/__init__.py
simmer/schemas/custom_validator.py
simmer/schemas/example_plotting.yml
simmer/schemas/plotting_schema.yml
simmer/schemas/read_yml.py
simmer/tests/__init__.py
simmer/tests/test_config.csv
simmer/tests/test_config_test_case.csv
simmer/tests/test_contrast.py
simmer/tests/test_image_config.csv
simmer/tests/test_validate.yml
simmer/tests/tests_io.py
simmer/tests/tests_reduction.py
simmer-1.1.1.dist-info/LICENSE
simmer-1.1.1.dist-info/METADATA
simmer-1.1.1.dist-info/WHEEL
simmer-1.1.1.dist-info/top_level.txt
simmer-1.1.1.dist-info/RECORD
