Metadata-Version: 2.1
Name: simmer
Version: 1.1.1
Summary: Stellar Image Maturation via Efficient Reduction
Author: Lea Hirsch, Holden Gill, Courtney D. Dressing, David R. Ciardi
Author-email: Arjun Savel <asavel@gmail.com>
License: MIT
Project-URL: Homepage, https://github.com/arjunsavel/SImMER
Project-URL: Issues, https://github.com/arjunsavel/SImMER/issues
Project-URL: Documentation, https://simmer.readthedocs.io
Keywords: astronomy
Classifier: Development Status :: 4 - Beta
Classifier: Intended Audience :: Developers
Classifier: Intended Audience :: Science/Research
Classifier: Natural Language :: English
Classifier: License :: OSI Approved :: MIT License
Classifier: Programming Language :: Python
Classifier: Programming Language :: Python :: 3.8
Classifier: Programming Language :: Python :: 3.9
Classifier: Topic :: Scientific/Engineering :: Astronomy
Requires-Python: >=3.8
License-File: LICENSE
Requires-Dist: numpy
Requires-Dist: tqdm
Requires-Dist: pandas ==1.2.3
Requires-Dist: astropy >=5.1
Requires-Dist: openpyxl >=2.5.12
Requires-Dist: scipy
Requires-Dist: matplotlib
Requires-Dist: Scikit-image >=0.16.2
Requires-Dist: pyyaml >=5.3.1
Requires-Dist: numba
Requires-Dist: emcee
Requires-Dist: cerberus >=1.3.2
Requires-Dist: photutils >=1.5.0
Provides-Extra: docs
Requires-Dist: nbsphinx ; extra == 'docs'
Requires-Dist: nbconvert ; extra == 'docs'
Requires-Dist: pygments >=2.4.2 ; extra == 'docs'
Requires-Dist: Jinja2 ==3.1.3 ; extra == 'docs'
Requires-Dist: sphinx-book-theme ; extra == 'docs'
